COPYING
MANIFEST.in
README
setup.cfg
setup.py
lava_android_test/__init__.py
lava_android_test/adb.py
lava_android_test/api.py
lava_android_test/commands.py
lava_android_test/config.py
lava_android_test/hwprofile.py
lava_android_test/main.py
lava_android_test/provider.py
lava_android_test/repository.py
lava_android_test/swprofile.py
lava_android_test/testdef.py
lava_android_test/utils.py
lava_android_test.egg-info/PKG-INFO
lava_android_test.egg-info/SOURCES.txt
lava_android_test.egg-info/dependency_links.txt
lava_android_test.egg-info/entry_points.txt
lava_android_test.egg-info/not-zip-safe
lava_android_test.egg-info/requires.txt
lava_android_test.egg-info/top_level.txt
lava_android_test/test_definitions/0xbench.py
lava_android_test/test_definitions/__init__.py
lava_android_test/test_definitions/big_LITTLE.py
lava_android_test/test_definitions/blackbox.py
lava_android_test/test_definitions/bluetooth.py
lava_android_test/test_definitions/busybox.py
lava_android_test/test_definitions/cache_coherency.py
lava_android_test/test_definitions/cts.py
lava_android_test/test_definitions/gatortest.py
lava_android_test/test_definitions/glmark2.py
lava_android_test/test_definitions/helloworld.py
lava_android_test/test_definitions/ime.py
lava_android_test/test_definitions/install_prep_4bench.py
lava_android_test/test_definitions/iozone.py
lava_android_test/test_definitions/memtester.py
lava_android_test/test_definitions/methanol.py
lava_android_test/test_definitions/mmtest.py
lava_android_test/test_definitions/monkey.py
lava_android_test/test_definitions/monkey_long_run.py
lava_android_test/test_definitions/pm-qa.py
lava_android_test/test_definitions/sched_tests.py
lava_android_test/test_definitions/skia.py
lava_android_test/test_definitions/sleep.py
lava_android_test/test_definitions/task_placement.py
lava_android_test/test_definitions/tjbench.py
lava_android_test/test_definitions/usbhardware.py
lava_android_test/test_definitions/v8.py
lava_android_test/test_definitions/wifi.py
lava_android_test/test_definitions/android-0xbenchmark/ZeroxBench_Preference.xml
lava_android_test/test_definitions/android-0xbenchmark/android_0xbenchmark_kill.py
lava_android_test/test_definitions/android-0xbenchmark/android_0xbenchmark_modify_path.py
